{"installations": 2070, "repositories": 58015, "suspended": 44, "popular": [{"id":16536608,"login":"guanguans","stars":7359},{"id":16170116,"login":"pterm","stars":2430},{"id":8132103,"login":"lukaszflorczak","stars":1378},{"id":21032759,"login":"theodorusclarence","stars":914},{"id":18889029,"login":"ALBINPRAVEEN","stars":868},{"id":16520765,"login":"nielse63","stars":644},{"id":7109391,"login":"kwebio","stars":623},{"id":9643344,"login":"pojntfx","stars":557},{"id":18812493,"login":"TotallyInformation","stars":486},{"id":12751378,"login":"CoreProc","stars":409}] }
